{
	"class" : {
		"DevelopmentSupport" : "CamilloBruni 1/10/2014 16:44",
		"baseConfigurationClassIfAbsent:" : "CamilloBruni 1/10/2014 16:44",
		"ensureMetacello" : "CamilloBruni 1/10/2014 16:44",
		"ensureMetacelloBaseConfiguration" : "CamilloBruni 1/10/2014 16:44",
		"isMetacelloConfig" : "CamilloBruni 1/10/2014 16:44",
		"load" : "CamilloBruni 1/10/2014 16:44",
		"loadBleedingEdge" : "CamilloBruni 1/10/2014 16:44",
		"loadDevelopment" : "CamilloBruni 1/10/2014 16:44",
		"project" : "CamilloBruni 1/10/2014 16:44",
		"validate" : "CamilloBruni 1/10/2014 16:44" },
	"instance" : {
		"baseline10:" : "CamilloBruni 1/19/2014 18:38",
		"customProjectAttributes" : "CamilloBruni 1/10/2014 16:44",
		"development:" : "CamilloBruni 1/19/2014 18:38",
		"fuelMetalevel:" : "CamilloBruni 1/10/2014 16:44",
		"osProcess:" : "CamilloBruni 1/19/2014 18:39",
		"project" : "CamilloBruni 1/10/2014 16:44",
		"stable:" : "CamilloBruni 1/10/2014 16:44",
		"versionDevelopment:" : "CamilloBruni 1/10/2014 16:45" } }
